anyHR/__init__.py
anyHR/constraint/Constraint.py
anyHR/constraint/Constraint2Tree.py
anyHR/constraint/ConstraintEvaluator.py
anyHR/constraint/ConstraintQuantitativeEvaluator.py
anyHR/constraint/ConstrainttoZ3.py
anyHR/constraint/ConstrainttoZ3Equality.py
anyHR/constraint/__init__.py
anyHR/constraint/node/Node.py
anyHR/constraint/node/SubstitutorVisitor.py
anyHR/constraint/node/Visitor.py
anyHR/constraint/node/__init__.py
anyHR/constraint/node/substitute.py
anyHR/constraint/parser/ConstraintLexer.py
anyHR/constraint/parser/ConstraintParser.py
anyHR/constraint/parser/ConstraintParserVisitor.py
anyHR/constraint/parser/__init__.py
anyHR/hit_and_run/__init__.py
anyHR/hit_and_run/hit_and_run.py
anyHR/pso/__init__.py
anyHR/pso/pso.py
anyHR-1.0.0.dist-info/LICENSE
anyHR-1.0.0.dist-info/METADATA
anyHR-1.0.0.dist-info/WHEEL
anyHR-1.0.0.dist-info/top_level.txt
anyHR-1.0.0.dist-info/RECORD
