Metadata-Version: 2.1
Name: anyHR
Version: 1.0.0
Summary: Library implementing hit-and-run methods for sampling open bounded sets.
Home-page: https://github.com/figlerg/anyHR
Author: Felix Gigler, Dejan Nickovic, Cristinel Mateis, Nicolas Basset, Thao Dang
Author-email: felix.gigler.fl@ait.ac.at, dejan.nickovic@ait.ac.at
License: BSD
Platform: UNKNOWN
Classifier: License :: OSI Approved :: BSD License
Classifier: Programming Language :: Python :: 3.5
Classifier: Programming Language :: Python :: 3.6
Classifier: Programming Language :: Python :: 3.7
Requires-Python: >=3.5
License-File: LICENSE
Requires-Dist: z3-solver
Requires-Dist: antlr4-python3-runtime
Requires-Dist: numpy
